{"AAVE_USDT": {"consecutive": 0, "last_alert": null, "start_time": null, "last_mid_price": 117.492}, "ADA_USDT": {"consecutive": 0, "last_alert": null, "start_time": null, "last_mid_price": 0.26285}, "ALGO_USDT": {"consecutive": 0, "last_alert": null, "start_time": null, "last_mid_price": 0.11357}, "BCH_USDT": {"consecutive": 0, "last_alert": null, "start_time": null, "last_mid_price": 451.35}, "BNB_USDT": {"consecutive": 0, "last_alert": null, "start_time": null, "last_mid_price": 642.38}, "BONK_USDT": {"consecutive": 0, "last_alert": null, "start_time": null, "last_mid_price": null}, "BTC_USDT": {"consecutive": 0, "last_alert": null, "start_time": null, "last_mid_price": 77242.48}, "CAKE_USDT": {"consecutive": 0, "last_alert": null, "start_time": null, "last_mid_price": 1.6139}, "CFX_USDT": {"consecutive": 0, "last_alert": null, "start_time": null, "last_mid_price": 0.0638}, "DASH_USDT": {"consecutive": 0, "last_alert": null, "start_time": null, "last_mid_price": 37.155}, "DOT_USDT": {"consecutive": 0, "last_alert": null, "start_time": null, "last_mid_price": 1.3467}, "DOGE_USDT": {"consecutive": 0, "last_alert": null, "start_time": null, "last_mid_price": 0.10071}, "ETH_USDT": {"consecutive": 0, "last_alert": null, "start_time": null, "last_mid_price": 2432.11}, "FARTCOIN_USDT": {"consecutive": 0, "last_alert": null, "start_time": null, "last_mid_price": 0.22452}, "FLOKI_USDT": {"consecutive": 0, "last_alert": null, "start_time": null, "last_mid_price": null}, "HYPE_USDT": {"consecutive": 0, "last_alert": null, "start_time": null, "last_mid_price": 44.046}, "LINK_USDT": {"consecutive": 0, "last_alert": null, "start_time": null, "last_mid_price": 9.819}, "LSK_USDT": {"consecutive": 0, "last_alert": null, "start_time": null, "last_mid_price": 0.1262}, "LTC_USDT": {"consecutive": 0, "last_alert": null, "start_time": null, "last_mid_price": 56.584}, "NEAR_USDT": {"consecutive": 0, "last_alert": null, "start_time": null, "last_mid_price": 1.4316}, "NOS_USDT": {"consecutive": 0, "last_alert": null, "start_time": null, "last_mid_price": 0.24093}, "PEPE_USDT": {"consecutive": 0, "last_alert": null, "start_time": null, "last_mid_price": null}, "POL_USDT": {"consecutive": 0, "last_alert": null, "start_time": null, "last_mid_price": 0.09028}, "QDX_USDT": {"consecutive": 0, "last_alert": null, "start_time": null, "last_mid_price": 0.01031}, "RENDER_USDT": {"consecutive": 0, "last_alert": null, "start_time": null, "last_mid_price": 1.89513}, "Sonic_USDT": {"consecutive": 0, "last_alert": null, "start_time": null, "last_mid_price": 0.04774}, "SHIB_USDT": {"consecutive": 1, "last_alert": null, "start_time": "2026-04-17T19:12:15.588764+01:00", "last_mid_price": null}, "SLP_USDT": {"consecutive": 0, "last_alert": null, "start_time": null, "last_mid_price": 0.0006534}, "SOL_USDT": {"consecutive": 0, "last_alert": null, "start_time": null, "last_mid_price": 89.8}, "STRK_USDT": {"consecutive": 0, "last_alert": null, "start_time": null, "last_mid_price": 0.03703}, "SUI_USDT": {"consecutive": 0, "last_alert": null, "start_time": null, "last_mid_price": 1.0039}, "TON_USDT": {"consecutive": 0, "last_alert": null, "start_time": null, "last_mid_price": 1.4178}, "TRX_USDT": {"consecutive": 0, "last_alert": null, "start_time": null, "last_mid_price": 0.32699}, "USDC_USDT": {"consecutive": 0, "last_alert": null, "start_time": null, "last_mid_price": 0.9991}, "WIF_USDT": {"consecutive": 0, "last_alert": null, "start_time": null, "last_mid_price": 0.2178}, "XLM_USDT": {"consecutive": 0, "last_alert": null, "start_time": null, "last_mid_price": 0.1725}, "XRP_USDT": {"consecutive": 0, "last_alert": null, "start_time": null, "last_mid_price": 1.4871}, "XYO_USDT": {"consecutive": 0, "last_alert": null, "start_time": null, "last_mid_price": 0.0037387}, "ZKSync_USDT": {"consecutive": 0, "last_alert": null, "start_time": null, "last_mid_price": 0.017158}, "BTC_NGN": {"consecutive": 0, "last_alert": null, "start_time": null, "last_mid_price": 106122524.0}, "USDT_NGN": {"consecutive": 5, "last_alert": "2026-04-17T19:13:12.833502+01:00", "start_time": "2026-04-17T15:30:57.280594+01:00", "last_mid_price": 1380.88}, "QDX_NGN": {"consecutive": 4, "last_alert": "2026-04-17T19:13:17.169616+01:00", "start_time": "2026-04-17T16:36:32.980776+01:00", "last_mid_price": 14.3}, "ETH_NGN": {"consecutive": 0, "last_alert": null, "start_time": null, "last_mid_price": 3350180.0}, "TRX_NGN": {"consecutive": 0, "last_alert": null, "start_time": null, "last_mid_price": 452.2628}, "XRP_NGN": {"consecutive": 0, "last_alert": null, "start_time": null, "last_mid_price": 2039.99}, "DASH_NGN": {"consecutive": 0, "last_alert": null, "start_time": null, "last_mid_price": 51865.0}, "LTC_NGN": {"consecutive": 0, "last_alert": null, "start_time": null, "last_mid_price": 78302.0}, "SOL_NGN": {"consecutive": 0, "last_alert": null, "start_time": null, "last_mid_price": 123503.36}, "USDC_NGN": {"consecutive": 2, "last_alert": null, "start_time": "2026-04-17T18:19:29.493002+01:00", "last_mid_price": 1380.0}, "USDT_GHS": {"consecutive": 0, "last_alert": null, "start_time": null, "last_mid_price": 11.66}, "CNGN_NGN": {"consecutive": 0, "last_alert": null, "start_time": null, "last_mid_price": 0.9995}, "USDT_CNGN": {"consecutive": 0, "last_alert": null, "start_time": null, "last_mid_price": 1395.0}}