{"AAVE_USDT": {"consecutive": 0, "last_alert": null, "start_time": null, "last_mid_price": 117.107}, "ADA_USDT": {"consecutive": 0, "last_alert": null, "start_time": null, "last_mid_price": 0.27254}, "ALGO_USDT": {"consecutive": 0, "last_alert": null, "start_time": null, "last_mid_price": 0.08945}, "BCH_USDT": {"consecutive": 0, "last_alert": null, "start_time": null, "last_mid_price": 459.72}, "BNB_USDT": {"consecutive": 0, "last_alert": null, "start_time": null, "last_mid_price": 653.65}, "BONK_USDT": {"consecutive": 0, "last_alert": null, "start_time": null, "last_mid_price": null}, "BTC_USDT": {"consecutive": 0, "last_alert": null, "start_time": null, "last_mid_price": 72498.42}, "CAKE_USDT": {"consecutive": 0, "last_alert": null, "start_time": null, "last_mid_price": 1.4}, "CFX_USDT": {"consecutive": 0, "last_alert": null, "start_time": null, "last_mid_price": 0.05092}, "DASH_USDT": {"consecutive": 0, "last_alert": null, "start_time": null, "last_mid_price": 34.287}, "DOT_USDT": {"consecutive": 0, "last_alert": null, "start_time": null, "last_mid_price": 1.5286}, "DOGE_USDT": {"consecutive": 0, "last_alert": null, "start_time": null, "last_mid_price": 0.0963}, "ETH_USDT": {"consecutive": 0, "last_alert": null, "start_time": null, "last_mid_price": 2125.73}, "FARTCOIN_USDT": {"consecutive": 0, "last_alert": null, "start_time": null, "last_mid_price": 0.17588}, "FLOKI_USDT": {"consecutive": 0, "last_alert": null, "start_time": null, "last_mid_price": null}, "HYPE_USDT": {"consecutive": 0, "last_alert": null, "start_time": null, "last_mid_price": 31.719}, "LINK_USDT": {"consecutive": 0, "last_alert": null, "start_time": null, "last_mid_price": 9.213}, "LSK_USDT": {"consecutive": 0, "last_alert": null, "start_time": null, "last_mid_price": 0.1326}, "LTC_USDT": {"consecutive": 0, "last_alert": null, "start_time": null, "last_mid_price": 56.766}, "NEAR_USDT": {"consecutive": 0, "last_alert": null, "start_time": null, "last_mid_price": 1.2837}, "NOS_USDT": {"consecutive": 0, "last_alert": null, "start_time": null, "last_mid_price": 0.17274}, "PEPE_USDT": {"consecutive": 0, "last_alert": null, "start_time": null, "last_mid_price": null}, "POL_USDT": {"consecutive": 0, "last_alert": null, "start_time": null, "last_mid_price": 0.1028}, "QDX_USDT": {"consecutive": 131, "last_alert": "2026-03-05T11:08:10.023399+01:00", "start_time": "2026-02-26T20:14:38.688633+01:00", "last_mid_price": 0.012}, "RENDER_USDT": {"consecutive": 0, "last_alert": null, "start_time": null, "last_mid_price": 1.375}, "Sonic_USDT": {"consecutive": 0, "last_alert": null, "start_time": null, "last_mid_price": 0.04166}, "SHIB_USDT": {"consecutive": 0, "last_alert": null, "start_time": null, "last_mid_price": null}, "SLP_USDT": {"consecutive": 0, "last_alert": null, "start_time": null, "last_mid_price": 0.0005409}, "SOL_USDT": {"consecutive": 0, "last_alert": null, "start_time": null, "last_mid_price": 91.202}, "STRK_USDT": {"consecutive": 0, "last_alert": null, "start_time": null, "last_mid_price": 0.04141}, "SUI_USDT": {"consecutive": 0, "last_alert": null, "start_time": null, "last_mid_price": 0.9515}, "TON_USDT": {"consecutive": 0, "last_alert": null, "start_time": null, "last_mid_price": 1.3419}, "TRX_USDT": {"consecutive": 0, "last_alert": null, "start_time": null, "last_mid_price": 0.28483}, "USDC_USDT": {"consecutive": 0, "last_alert": null, "start_time": null, "last_mid_price": 1.0}, "WIF_USDT": {"consecutive": 0, "last_alert": null, "start_time": null, "last_mid_price": 0.2131}, "XLM_USDT": {"consecutive": 0, "last_alert": null, "start_time": null, "last_mid_price": 0.15888}, "XRP_USDT": {"consecutive": 0, "last_alert": null, "start_time": null, "last_mid_price": 1.4275}, "XYO_USDT": {"consecutive": 0, "last_alert": null, "start_time": null, "last_mid_price": 0.0042212}, "ZKSync_USDT": {"consecutive": 0, "last_alert": null, "start_time": null, "last_mid_price": 0.018813}, "BTC_NGN": {"consecutive": 0, "last_alert": null, "start_time": null, "last_mid_price": 101669452.0}, "USDT_NGN": {"consecutive": 14, "last_alert": "2026-03-05T11:09:30.533299+01:00", "start_time": "2026-03-04T19:04:40.782301+01:00", "last_mid_price": 1403.09}, "QDX_NGN": {"consecutive": 0, "last_alert": null, "start_time": null, "last_mid_price": 17.78}, "ETH_NGN": {"consecutive": 0, "last_alert": null, "start_time": null, "last_mid_price": 2976968.0}, "TRX_NGN": {"consecutive": 0, "last_alert": null, "start_time": null, "last_mid_price": 398.7373}, "XRP_NGN": {"consecutive": 0, "last_alert": null, "start_time": null, "last_mid_price": 2005.44}, "DASH_NGN": {"consecutive": 0, "last_alert": null, "start_time": null, "last_mid_price": 48981.0}, "LTC_NGN": {"consecutive": 0, "last_alert": null, "start_time": null, "last_mid_price": 79892.0}, "SOL_NGN": {"consecutive": 0, "last_alert": null, "start_time": null, "last_mid_price": 127933.42}, "USDC_NGN": {"consecutive": 0, "last_alert": null, "start_time": null, "last_mid_price": 1398.68}, "USDT_GHS": {"consecutive": 0, "last_alert": null, "start_time": null, "last_mid_price": 11.56}, "CNGN_NGN": {"consecutive": 188, "last_alert": "2026-03-05T11:10:11.455695+01:00", "start_time": "2026-02-23T12:15:17.126294+01:00", "last_mid_price": 0.9995}, "USDT_CNGN": {"consecutive": 0, "last_alert": null, "start_time": null, "last_mid_price": 1385.0}}