{"AAVE_USDT": {"consecutive": 0, "last_alert": null, "start_time": null, "last_mid_price": 111.909}, "ADA_USDT": {"consecutive": 0, "last_alert": null, "start_time": null, "last_mid_price": 0.26447}, "ALGO_USDT": {"consecutive": 0, "last_alert": null, "start_time": null, "last_mid_price": 0.08895}, "BCH_USDT": {"consecutive": 0, "last_alert": null, "start_time": null, "last_mid_price": 468.81}, "BNB_USDT": {"consecutive": 0, "last_alert": null, "start_time": null, "last_mid_price": 643.18}, "BONK_USDT": {"consecutive": 0, "last_alert": null, "start_time": null, "last_mid_price": null}, "BTC_USDT": {"consecutive": 0, "last_alert": null, "start_time": null, "last_mid_price": 70544.88}, "CAKE_USDT": {"consecutive": 0, "last_alert": null, "start_time": null, "last_mid_price": 1.3764}, "CFX_USDT": {"consecutive": 0, "last_alert": null, "start_time": null, "last_mid_price": 0.06283}, "DASH_USDT": {"consecutive": 0, "last_alert": null, "start_time": null, "last_mid_price": 32.368}, "DOT_USDT": {"consecutive": 0, "last_alert": null, "start_time": null, "last_mid_price": 1.4932}, "DOGE_USDT": {"consecutive": 0, "last_alert": null, "start_time": null, "last_mid_price": 0.09399}, "ETH_USDT": {"consecutive": 0, "last_alert": null, "start_time": null, "last_mid_price": 2156.92}, "FARTCOIN_USDT": {"consecutive": 0, "last_alert": null, "start_time": null, "last_mid_price": 0.19879}, "FLOKI_USDT": {"consecutive": 0, "last_alert": null, "start_time": null, "last_mid_price": null}, "HYPE_USDT": {"consecutive": 0, "last_alert": null, "start_time": null, "last_mid_price": 40.328}, "LINK_USDT": {"consecutive": 0, "last_alert": null, "start_time": null, "last_mid_price": 9.073}, "LSK_USDT": {"consecutive": 0, "last_alert": null, "start_time": null, "last_mid_price": 0.1303}, "LTC_USDT": {"consecutive": 0, "last_alert": null, "start_time": null, "last_mid_price": 55.914}, "NEAR_USDT": {"consecutive": 0, "last_alert": null, "start_time": null, "last_mid_price": 1.3286}, "NOS_USDT": {"consecutive": 0, "last_alert": null, "start_time": null, "last_mid_price": 0.29215}, "PEPE_USDT": {"consecutive": 0, "last_alert": null, "start_time": null, "last_mid_price": null}, "POL_USDT": {"consecutive": 0, "last_alert": null, "start_time": null, "last_mid_price": 0.09576}, "QDX_USDT": {"consecutive": 45, "last_alert": "2026-03-21T21:48:50.086205+01:00", "start_time": "2026-03-19T20:19:25.482946+01:00", "last_mid_price": 0.01301}, "RENDER_USDT": {"consecutive": 0, "last_alert": null, "start_time": null, "last_mid_price": 1.7085}, "Sonic_USDT": {"consecutive": 0, "last_alert": null, "start_time": null, "last_mid_price": 0.04513}, "SHIB_USDT": {"consecutive": 0, "last_alert": null, "start_time": null, "last_mid_price": null}, "SLP_USDT": {"consecutive": 0, "last_alert": null, "start_time": null, "last_mid_price": 0.0006623}, "SOL_USDT": {"consecutive": 0, "last_alert": null, "start_time": null, "last_mid_price": 89.87}, "STRK_USDT": {"consecutive": 0, "last_alert": null, "start_time": null, "last_mid_price": 0.03825}, "SUI_USDT": {"consecutive": 0, "last_alert": null, "start_time": null, "last_mid_price": 0.9656}, "TON_USDT": {"consecutive": 0, "last_alert": null, "start_time": null, "last_mid_price": 1.2591}, "TRX_USDT": {"consecutive": 0, "last_alert": null, "start_time": null, "last_mid_price": 0.31167}, "USDC_USDT": {"consecutive": 0, "last_alert": null, "start_time": null, "last_mid_price": 1.0002}, "WIF_USDT": {"consecutive": 0, "last_alert": null, "start_time": null, "last_mid_price": 0.1774}, "XLM_USDT": {"consecutive": 0, "last_alert": null, "start_time": null, "last_mid_price": 0.16564}, "XRP_USDT": {"consecutive": 0, "last_alert": null, "start_time": null, "last_mid_price": 1.4399}, "XYO_USDT": {"consecutive": 0, "last_alert": null, "start_time": null, "last_mid_price": 0.0039203}, "ZKSync_USDT": {"consecutive": 0, "last_alert": null, "start_time": null, "last_mid_price": 0.018834}, "BTC_NGN": {"consecutive": 1, "last_alert": null, "start_time": "2026-03-21T21:49:42.797261+01:00", "last_mid_price": 98766912.0}, "USDT_NGN": {"consecutive": 3, "last_alert": "2026-03-21T21:49:46.595533+01:00", "start_time": "2026-03-21T20:00:42.625201+01:00", "last_mid_price": 1397.01}, "QDX_NGN": {"consecutive": 0, "last_alert": null, "start_time": null, "last_mid_price": 18.82}, "ETH_NGN": {"consecutive": 1, "last_alert": null, "start_time": "2026-03-21T21:49:52.664860+01:00", "last_mid_price": 3001892.0}, "TRX_NGN": {"consecutive": 0, "last_alert": null, "start_time": null, "last_mid_price": 435.6481}, "XRP_NGN": {"consecutive": 0, "last_alert": null, "start_time": null, "last_mid_price": 2006.21}, "DASH_NGN": {"consecutive": 0, "last_alert": null, "start_time": null, "last_mid_price": 45710.0}, "LTC_NGN": {"consecutive": 0, "last_alert": null, "start_time": null, "last_mid_price": 78324.0}, "SOL_NGN": {"consecutive": 0, "last_alert": null, "start_time": null, "last_mid_price": 126488.14}, "USDC_NGN": {"consecutive": 0, "last_alert": null, "start_time": null, "last_mid_price": 1394.95}, "USDT_GHS": {"consecutive": 0, "last_alert": null, "start_time": null, "last_mid_price": 11.67}, "CNGN_NGN": {"consecutive": 488, "last_alert": "2026-03-21T21:50:14.788165+01:00", "start_time": "2026-02-23T12:15:17.126294+01:00", "last_mid_price": 1.001}, "USDT_CNGN": {"consecutive": 0, "last_alert": null, "start_time": null, "last_mid_price": 1425.0}}