{"AAVE_USDT": {"consecutive": 0, "last_alert": null, "start_time": null, "last_mid_price": 118.876}, "ADA_USDT": {"consecutive": 0, "last_alert": null, "start_time": null, "last_mid_price": 0.28766}, "ALGO_USDT": {"consecutive": 0, "last_alert": null, "start_time": null, "last_mid_price": 0.09308}, "BCH_USDT": {"consecutive": 0, "last_alert": null, "start_time": null, "last_mid_price": 471.63}, "BNB_USDT": {"consecutive": 0, "last_alert": null, "start_time": null, "last_mid_price": 680.29}, "BONK_USDT": {"consecutive": 0, "last_alert": null, "start_time": null, "last_mid_price": null}, "BTC_USDT": {"consecutive": 0, "last_alert": null, "start_time": null, "last_mid_price": 73290.92}, "CAKE_USDT": {"consecutive": 0, "last_alert": null, "start_time": null, "last_mid_price": 1.5134}, "CFX_USDT": {"consecutive": 0, "last_alert": null, "start_time": null, "last_mid_price": 0.06295}, "DASH_USDT": {"consecutive": 0, "last_alert": null, "start_time": null, "last_mid_price": 34.723}, "DOT_USDT": {"consecutive": 0, "last_alert": null, "start_time": null, "last_mid_price": 1.5979}, "DOGE_USDT": {"consecutive": 0, "last_alert": null, "start_time": null, "last_mid_price": 0.09999}, "ETH_USDT": {"consecutive": 0, "last_alert": null, "start_time": null, "last_mid_price": 2264.04}, "FARTCOIN_USDT": {"consecutive": 0, "last_alert": null, "start_time": null, "last_mid_price": 0.18442}, "FLOKI_USDT": {"consecutive": 0, "last_alert": null, "start_time": null, "last_mid_price": null}, "HYPE_USDT": {"consecutive": 0, "last_alert": null, "start_time": null, "last_mid_price": 39.223}, "LINK_USDT": {"consecutive": 0, "last_alert": null, "start_time": null, "last_mid_price": 9.643}, "LSK_USDT": {"consecutive": 0, "last_alert": null, "start_time": null, "last_mid_price": 0.1326}, "LTC_USDT": {"consecutive": 0, "last_alert": null, "start_time": null, "last_mid_price": 57.144}, "NEAR_USDT": {"consecutive": 0, "last_alert": null, "start_time": null, "last_mid_price": 1.3604}, "NOS_USDT": {"consecutive": 0, "last_alert": null, "start_time": null, "last_mid_price": 0.25799}, "PEPE_USDT": {"consecutive": 0, "last_alert": null, "start_time": null, "last_mid_price": null}, "POL_USDT": {"consecutive": 0, "last_alert": null, "start_time": null, "last_mid_price": 0.10058}, "QDX_USDT": {"consecutive": 342, "last_alert": "2026-03-16T12:18:12.732913+01:00", "start_time": "2026-02-26T20:14:38.688633+01:00", "last_mid_price": 0.0145}, "RENDER_USDT": {"consecutive": 0, "last_alert": null, "start_time": null, "last_mid_price": 1.83605}, "Sonic_USDT": {"consecutive": 0, "last_alert": null, "start_time": null, "last_mid_price": 0.05156}, "SHIB_USDT": {"consecutive": 0, "last_alert": null, "start_time": null, "last_mid_price": null}, "SLP_USDT": {"consecutive": 0, "last_alert": null, "start_time": null, "last_mid_price": 0.0006143}, "SOL_USDT": {"consecutive": 1, "last_alert": null, "start_time": "2026-03-16T12:18:33.358601+01:00", "last_mid_price": 93.484}, "STRK_USDT": {"consecutive": 0, "last_alert": null, "start_time": null, "last_mid_price": 0.04054}, "SUI_USDT": {"consecutive": 0, "last_alert": null, "start_time": null, "last_mid_price": 1.0442}, "TON_USDT": {"consecutive": 0, "last_alert": null, "start_time": null, "last_mid_price": 1.3244}, "TRX_USDT": {"consecutive": 0, "last_alert": null, "start_time": null, "last_mid_price": 0.29765}, "USDC_USDT": {"consecutive": 0, "last_alert": null, "start_time": null, "last_mid_price": 0.9996}, "WIF_USDT": {"consecutive": 0, "last_alert": null, "start_time": null, "last_mid_price": 0.1822}, "XLM_USDT": {"consecutive": 0, "last_alert": null, "start_time": null, "last_mid_price": 0.17207}, "XRP_USDT": {"consecutive": 0, "last_alert": null, "start_time": null, "last_mid_price": 1.474}, "XYO_USDT": {"consecutive": 0, "last_alert": null, "start_time": null, "last_mid_price": 0.0040397}, "ZKSync_USDT": {"consecutive": 0, "last_alert": null, "start_time": null, "last_mid_price": 0.020201}, "BTC_NGN": {"consecutive": 1, "last_alert": null, "start_time": "2026-03-16T12:19:21.637185+01:00", "last_mid_price": 103305072.0}, "USDT_NGN": {"consecutive": 1, "last_alert": null, "start_time": "2026-03-16T12:19:25.855199+01:00", "last_mid_price": 1405.0}, "QDX_NGN": {"consecutive": 0, "last_alert": null, "start_time": null, "last_mid_price": 17.84}, "ETH_NGN": {"consecutive": 0, "last_alert": null, "start_time": null, "last_mid_price": 3194940.0}, "TRX_NGN": {"consecutive": 0, "last_alert": null, "start_time": null, "last_mid_price": 420.1072}, "XRP_NGN": {"consecutive": 0, "last_alert": null, "start_time": null, "last_mid_price": 2065.8}, "DASH_NGN": {"consecutive": 0, "last_alert": null, "start_time": null, "last_mid_price": 48608.0}, "LTC_NGN": {"consecutive": 0, "last_alert": null, "start_time": null, "last_mid_price": 80910.0}, "SOL_NGN": {"consecutive": 0, "last_alert": null, "start_time": null, "last_mid_price": 131195.6}, "USDC_NGN": {"consecutive": 0, "last_alert": null, "start_time": null, "last_mid_price": 1409.68}, "USDT_GHS": {"consecutive": 0, "last_alert": null, "start_time": null, "last_mid_price": 11.53}, "CNGN_NGN": {"consecutive": 399, "last_alert": "2026-03-16T12:20:03.669410+01:00", "start_time": "2026-02-23T12:15:17.126294+01:00", "last_mid_price": 0.9994}, "USDT_CNGN": {"consecutive": 0, "last_alert": null, "start_time": null, "last_mid_price": 1425.0}}