{"AAVE_USDT": {"consecutive": 0, "last_alert": null, "start_time": null, "last_mid_price": 91.181, "stale_ob_count": 0, "last_ob_snapshot": {"ba_p": 91.067, "ba_a": 7.6556, "bb_p": 90.898, "bb_a": 21.5259}}, "ADA_USDT": {"consecutive": 0, "last_alert": null, "start_time": null, "last_mid_price": 0.25636, "stale_ob_count": 0, "last_ob_snapshot": {"ba_p": 0.25684, "ba_a": 16910.0, "bb_p": 0.25606, "bb_a": 12130.0}}, "ALGO_USDT": {"consecutive": 0, "last_alert": null, "start_time": null, "last_mid_price": 0.11076, "stale_ob_count": 0, "last_ob_snapshot": {"ba_p": 0.11086, "ba_a": 12530.0, "bb_p": 0.10864, "bb_a": 12600.0}}, "BCH_USDT": {"consecutive": 0, "last_alert": null, "start_time": null, "last_mid_price": 414.06, "stale_ob_count": 0, "last_ob_snapshot": {"ba_p": 414.74, "ba_a": 1.7564, "bb_p": 413.56, "bb_a": 0.6004}}, "BNB_USDT": {"consecutive": 0, "last_alert": null, "start_time": null, "last_mid_price": 655.62, "stale_ob_count": 0, "last_ob_snapshot": {"ba_p": 655.61, "ba_a": 2.45208, "bb_p": 653.63, "bb_a": 1.40696}}, "BONK_USDT": {"consecutive": 0, "last_alert": null, "start_time": null, "last_mid_price": null, "stale_ob_count": 0, "last_ob_snapshot": {"ba_p": 6.3e-06, "ba_a": 38190000.0, "bb_p": 6.17e-06, "bb_a": 44430000.0}}, "BTC_USDT": {"consecutive": 0, "last_alert": null, "start_time": null, "last_mid_price": 78386.83, "stale_ob_count": 0, "last_ob_snapshot": {"ba_p": 78431.26, "ba_a": 0.3954431, "bb_p": 78277.94, "bb_a": 0.0705759}}, "CAKE_USDT": {"consecutive": 0, "last_alert": null, "start_time": null, "last_mid_price": 1.4697, "stale_ob_count": 0, "last_ob_snapshot": {"ba_p": 1.4763, "ba_a": 1630.0, "bb_p": 1.4707, "bb_a": 217.188}}, "CFX_USDT": {"consecutive": 0, "last_alert": null, "start_time": null, "last_mid_price": 0.06429, "stale_ob_count": 0, "last_ob_snapshot": {"ba_p": 0.06415, "ba_a": 18620.0, "bb_p": 0.06287, "bb_a": 5610.0}}, "DASH_USDT": {"consecutive": 0, "last_alert": null, "start_time": null, "last_mid_price": 42.472, "stale_ob_count": 0, "last_ob_snapshot": {"ba_p": 42.1, "ba_a": 6.84802, "bb_p": 41.261, "bb_a": 13.39075}}, "DOT_USDT": {"consecutive": 0, "last_alert": null, "start_time": null, "last_mid_price": 1.2841, "stale_ob_count": 0, "last_ob_snapshot": {"ba_p": 1.2867, "ba_a": 1480.0, "bb_p": 1.2823, "bb_a": 2700.0}}, "DOGE_USDT": {"consecutive": 0, "last_alert": null, "start_time": null, "last_mid_price": 0.11152, "stale_ob_count": 0, "last_ob_snapshot": {"ba_p": 0.11174, "ba_a": 32620.0, "bb_p": 0.11143, "bb_a": 8860.0}}, "ETH_USDT": {"consecutive": 0, "last_alert": null, "start_time": null, "last_mid_price": 2186.79, "stale_ob_count": 0, "last_ob_snapshot": {"ba_p": 2194.7, "ba_a": 2.5686901, "bb_p": 2189.22, "bb_a": 3.0562445}}, "FARTCOIN_USDT": {"consecutive": 0, "last_alert": null, "start_time": null, "last_mid_price": 0.19256, "stale_ob_count": 0, "last_ob_snapshot": {"ba_p": 0.19588, "ba_a": 3680.0, "bb_p": 0.19197, "bb_a": 1830.0}}, "FLOKI_USDT": {"consecutive": 0, "last_alert": null, "start_time": null, "last_mid_price": null, "stale_ob_count": 0, "last_ob_snapshot": {"ba_p": 3.206e-05, "ba_a": 455070.0, "bb_p": 3.188e-05, "bb_a": 14780000.0}}, "HYPE_USDT": {"consecutive": 0, "last_alert": null, "start_time": null, "last_mid_price": 43.329, "stale_ob_count": 0, "last_ob_snapshot": {"ba_p": 43.259, "ba_a": 3.3549, "bb_p": 42.397, "bb_a": 0.807}}, "LINK_USDT": {"consecutive": 0, "last_alert": null, "start_time": null, "last_mid_price": 9.79, "stale_ob_count": 0, "last_ob_snapshot": {"ba_p": 9.801, "ba_a": 3.172, "bb_p": 9.774, "bb_a": 6.384}}, "LSK_USDT": {"consecutive": 0, "last_alert": null, "start_time": null, "last_mid_price": 0.1422, "stale_ob_count": 0, "last_ob_snapshot": {"ba_p": 0.1218, "ba_a": 4620.0, "bb_p": 0.1198, "bb_a": 4680.0}}, "LTC_USDT": {"consecutive": 0, "last_alert": null, "start_time": null, "last_mid_price": 56.235, "stale_ob_count": 0, "last_ob_snapshot": {"ba_p": 56.405, "ba_a": 18.65965, "bb_p": 56.245, "bb_a": 8.37307}}, "NEAR_USDT": {"consecutive": 0, "last_alert": null, "start_time": null, "last_mid_price": 1.561, "stale_ob_count": 0, "last_ob_snapshot": {"ba_p": 1.5548, "ba_a": 274.3294, "bb_p": 1.5237, "bb_a": 309.5627}}, "NOS_USDT": {"consecutive": 0, "last_alert": null, "start_time": null, "last_mid_price": 0.30181, "stale_ob_count": 0, "last_ob_snapshot": {"ba_p": 0.3011, "ba_a": 173.0339, "bb_p": 0.2951, "bb_a": 179.0222}}, "PEPE_USDT": {"consecutive": 0, "last_alert": null, "start_time": null, "last_mid_price": null, "stale_ob_count": 0, "last_ob_snapshot": {"ba_p": 3.79e-06, "ba_a": 45590000.0, "bb_p": 3.77e-06, "bb_a": 719280.0}}, "POL_USDT": {"consecutive": 0, "last_alert": null, "start_time": null, "last_mid_price": 0.09217, "stale_ob_count": 0, "last_ob_snapshot": {"ba_p": 0.09241, "ba_a": 203.98, "bb_p": 0.09189, "bb_a": 328.24}}, "QDX_USDT": {"consecutive": 181, "last_alert": "2026-05-07T16:11:10.406317+01:00", "start_time": "2026-05-03T14:54:45.955391+01:00", "last_mid_price": 0.0096, "stale_ob_count": 0, "last_ob_snapshot": {"ba_p": 0.00959, "ba_a": 3760.0, "bb_p": 0.00838, "bb_a": 1710.0}}, "RENDER_USDT": {"consecutive": 0, "last_alert": null, "start_time": null, "last_mid_price": 1.81831, "stale_ob_count": 0, "last_ob_snapshot": {"ba_p": 1.84719, "ba_a": 129.5425, "bb_p": 1.81043, "bb_a": 169.3948}}, "Sonic_USDT": {"consecutive": 0, "last_alert": null, "start_time": null, "last_mid_price": 0.04584, "stale_ob_count": 0, "last_ob_snapshot": {"ba_p": 0.04562, "ba_a": 6300.0, "bb_p": 0.0447, "bb_a": 3140.0}}, "SHIB_USDT": {"consecutive": 0, "last_alert": null, "start_time": null, "last_mid_price": null, "stale_ob_count": 0, "last_ob_snapshot": {"ba_p": 5.85e-06, "ba_a": 3000000.0, "bb_p": 5.82e-06, "bb_a": 9260000.0}}, "SLP_USDT": {"consecutive": 0, "last_alert": null, "start_time": null, "last_mid_price": 0.0006632, "stale_ob_count": 0, "last_ob_snapshot": {"ba_p": 0.0006746, "ba_a": 577910.0, "bb_p": 0.0006611, "bb_a": 464550.0}}, "SOL_USDT": {"consecutive": 0, "last_alert": null, "start_time": null, "last_mid_price": 86.739, "stale_ob_count": 0, "last_ob_snapshot": {"ba_p": 86.977, "ba_a": 11.3884, "bb_p": 86.759, "bb_a": 20.0703}}, "STRK_USDT": {"consecutive": 0, "last_alert": null, "start_time": null, "last_mid_price": 0.04284, "stale_ob_count": 0, "last_ob_snapshot": {"ba_p": 0.04284, "ba_a": 808.5375, "bb_p": 0.04198, "bb_a": 671.0092}}, "SUI_USDT": {"consecutive": 0, "last_alert": null, "start_time": null, "last_mid_price": 1.0806, "stale_ob_count": 0, "last_ob_snapshot": {"ba_p": 1.0812, "ba_a": 211.4782, "bb_p": 1.0596, "bb_a": 350.5887}}, "TON_USDT": {"consecutive": 0, "last_alert": null, "start_time": null, "last_mid_price": 1.9564, "stale_ob_count": 0, "last_ob_snapshot": {"ba_p": 1.962, "ba_a": 2.94, "bb_p": 1.956, "bb_a": 1800.0}}, "TRX_USDT": {"consecutive": 0, "last_alert": null, "start_time": null, "last_mid_price": 0.35584, "stale_ob_count": 0, "last_ob_snapshot": {"ba_p": 0.35654, "ba_a": 20870.0, "bb_p": 0.35546, "bb_a": 67550.0}}, "USDC_USDT": {"consecutive": 0, "last_alert": null, "start_time": null, "last_mid_price": 0.9999, "stale_ob_count": 0, "last_ob_snapshot": {"ba_p": 1.0003, "ba_a": 67260.0, "bb_p": 0.9999, "bb_a": 246760.0}}, "WIF_USDT": {"consecutive": 0, "last_alert": null, "start_time": null, "last_mid_price": 0.1999, "stale_ob_count": 0, "last_ob_snapshot": {"ba_p": 0.2005, "ba_a": 152.229, "bb_p": 0.1965, "bb_a": 973.196}}, "XLM_USDT": {"consecutive": 0, "last_alert": null, "start_time": null, "last_mid_price": 0.15243, "stale_ob_count": 0, "last_ob_snapshot": {"ba_p": 0.15233, "ba_a": 38100.0, "bb_p": 0.15177, "bb_a": 5940.0}}, "XRP_USDT": {"consecutive": 0, "last_alert": null, "start_time": null, "last_mid_price": 1.4219, "stale_ob_count": 0, "last_ob_snapshot": {"ba_p": 1.4253, "ba_a": 578.25, "bb_p": 1.421, "bb_a": 1340.0}}, "XYO_USDT": {"consecutive": 0, "last_alert": null, "start_time": null, "last_mid_price": 0.0039203, "stale_ob_count": 0, "last_ob_snapshot": {"ba_p": 0.0038593, "ba_a": 1230.0, "bb_p": 0.0038009, "bb_a": 24210.0}}, "ZKSync_USDT": {"consecutive": 0, "last_alert": null, "start_time": null, "last_mid_price": 0.015661, "stale_ob_count": 0, "last_ob_snapshot": {"ba_p": 0.015849, "ba_a": 9540.0, "bb_p": 0.015533, "bb_a": 5570.0}}, "BTC_NGN": {"consecutive": 0, "last_alert": null, "start_time": null, "last_mid_price": 107826911.0, "stale_ob_count": 0, "last_ob_snapshot": {"ba_p": 108378590.0, "ba_a": 1.10946176, "bb_p": 107837507.0, "bb_a": 1.10013526}}, "USDT_NGN": {"consecutive": 0, "last_alert": null, "start_time": null, "last_mid_price": 1380.13, "stale_ob_count": 0, "last_ob_snapshot": {"ba_p": 1383.78, "ba_a": 149.4094, "bb_p": 1380.13, "bb_a": 4390.0}}, "QDX_NGN": {"consecutive": 0, "last_alert": null, "start_time": null, "last_mid_price": 12.37, "stale_ob_count": 0, "last_ob_snapshot": {"ba_p": 12.79, "ba_a": 1420.0, "bb_p": 12.37, "bb_a": 1650.0}}, "ETH_NGN": {"consecutive": 0, "last_alert": null, "start_time": null, "last_mid_price": 3020173.0, "stale_ob_count": 0, "last_ob_snapshot": {"ba_p": 3026202.0, "ba_a": 0.0270857, "bb_p": 3017965.0, "bb_a": 0.0006289}}, "TRX_NGN": {"consecutive": 0, "last_alert": null, "start_time": null, "last_mid_price": 489.64, "stale_ob_count": 0, "last_ob_snapshot": {"ba_p": 492.6501, "ba_a": 20890.0, "bb_p": 490.1905, "bb_a": 38980.0}}, "XRP_NGN": {"consecutive": 0, "last_alert": null, "start_time": null, "last_mid_price": 1958.5, "stale_ob_count": 0, "last_ob_snapshot": {"ba_p": 1968.24, "ba_a": 2240.0, "bb_p": 1958.4, "bb_a": 2880.0}}, "DASH_NGN": {"consecutive": 0, "last_alert": null, "start_time": null, "last_mid_price": 58062.0, "stale_ob_count": 0, "last_ob_snapshot": {"ba_p": 57937.0, "ba_a": 30.90844, "bb_p": 57665.0, "bb_a": 2.0}}, "LTC_NGN": {"consecutive": 0, "last_alert": null, "start_time": null, "last_mid_price": 77643.0, "stale_ob_count": 0, "last_ob_snapshot": {"ba_p": 77937.0, "ba_a": 145.11187, "bb_p": 77546.0, "bb_a": 133.92076}}, "SOL_NGN": {"consecutive": 0, "last_alert": null, "start_time": null, "last_mid_price": 120248.92, "stale_ob_count": 0, "last_ob_snapshot": {"ba_p": 120221.25, "ba_a": 65.1849, "bb_p": 119385.99, "bb_a": 0.0052}}, "USDC_NGN": {"consecutive": 0, "last_alert": null, "start_time": null, "last_mid_price": 1382.88, "stale_ob_count": 0, "last_ob_snapshot": {"ba_p": 1382.88, "ba_a": 312.2389, "bb_p": 1379.0, "bb_a": 1270.0}}, "USDT_GHS": {"consecutive": 0, "last_alert": null, "start_time": null, "last_mid_price": 11.85, "stale_ob_count": 0, "last_ob_snapshot": {"ba_p": 12.02, "ba_a": 3780.0, "bb_p": 11.82, "bb_a": 5240.0}}, "CNGN_NGN": {"consecutive": 0, "last_alert": null, "start_time": null, "last_mid_price": 0.9995, "stale_ob_count": 2, "last_ob_snapshot": {"ba_p": 1.0005, "ba_a": 420730.0, "bb_p": 0.9995, "bb_a": 676840.0}}, "USDT_CNGN": {"consecutive": 0, "last_alert": null, "start_time": null, "last_mid_price": 1381.8, "stale_ob_count": 2, "last_ob_snapshot": {"ba_p": 1386.0, "ba_a": 1450.0, "bb_p": 1381.8, "bb_a": 968.3133}}}